pinclr/__init__.py
lawson-0.0.1.dist-info/METADATA
lawson-0.0.1.dist-info/WHEEL
lawson-0.0.1.dist-info/top_level.txt
lawson-0.0.1.dist-info/RECORD
